FRBUS/__init__.py
FRBUS/computation.py
FRBUS/processing.py
FRBUS/punchcard.py
FRBUS/sim_setup.py
FRBUS-1.0.dist-info/METADATA
FRBUS-1.0.dist-info/WHEEL
FRBUS-1.0.dist-info/top_level.txt
FRBUS-1.0.dist-info/RECORD
