Metadata-Version: 2.1
Name: FRBUS
Version: 1.0
Author: Yale Budget Lab
Requires-Dist: pandas
Requires-Dist: scipy
Requires-Dist: numpy
Requires-Dist: black
Requires-Dist: flake8
Requires-Dist: mypy
Requires-Dist: typing-extensions
Requires-Dist: multiprocess
Requires-Dist: sympy ==1.3
Requires-Dist: symengine
Requires-Dist: matplotlib
Requires-Dist: lxml
Requires-Dist: networkx
Requires-Dist: scikit-umfpack ==0.3.3
Requires-Dist: pyfrbus
